awsume/__data__.py
awsume/__init__.py
awsume/autoawsume/__init__.py
awsume/autoawsume/main.py
awsume/autoawsume/process.py
awsume/awsumepy/__init__.py
awsume/awsumepy/app.py
awsume/awsumepy/awsume.py
awsume/awsumepy/default_plugins.py
awsume/awsumepy/hookimpl.py
awsume/awsumepy/hookspec.py
awsume/awsumepy/main.py
awsume/awsumepy/lib/__init__.py
awsume/awsumepy/lib/autoawsume.py
awsume/awsumepy/lib/autocomplete.py
awsume/awsumepy/lib/aws.py
awsume/awsumepy/lib/aws_files.py
awsume/awsumepy/lib/cache.py
awsume/awsumepy/lib/config_management.py
awsume/awsumepy/lib/constants.py
awsume/awsumepy/lib/exceptions.py
awsume/awsumepy/lib/logger.py
awsume/awsumepy/lib/profile.py
awsume/awsumepy/lib/safe_print.py
awsume/awsumepy/lib/saml.py
awsume/configure/__init__.py
awsume/configure/alias.py
awsume/configure/autocomplete.py
awsume/configure/main.py
awsume/configure/post_install.py
awsume-4.5.4.data/scripts/awsume
awsume-4.5.4.data/scripts/awsume.bat
awsume-4.5.4.data/scripts/awsume.fish
awsume-4.5.4.data/scripts/awsume.ps1
awsume_autocomplete/__init__.py
awsume_autocomplete/awsume_autocomplete.py
awsume-4.5.4.dist-info/LICENSE
awsume-4.5.4.dist-info/METADATA
awsume-4.5.4.dist-info/WHEEL
awsume-4.5.4.dist-info/entry_points.txt
awsume-4.5.4.dist-info/top_level.txt
awsume-4.5.4.dist-info/RECORD
